forex/.coverage
forex/.models.py.swp
forex/__init__.py
forex/__init__.pyc
forex/admin.py
forex/admin.pyc
forex/models.py
forex/models.pyc
forex/migrations/0001_initial.py
forex/migrations/0001_initial.pyc
forex/migrations/0002_auto_20150508_1326.py
forex/migrations/0002_auto_20150508_1326.pyc
forex/migrations/0003_auto_20150508_1447.py
forex/migrations/0003_auto_20150508_1447.pyc
forex/migrations/0004_auto_20150508_1504.py
forex/migrations/0004_auto_20150508_1504.pyc
forex/migrations/0005_auto_20150522_1402.py
forex/migrations/0005_auto_20150522_1402.pyc
forex/migrations/0006_auto_20150524_1013.py
forex/migrations/0006_auto_20150524_1013.pyc
forex/migrations/0007_auto_20150526_1255.py
forex/migrations/0007_auto_20150526_1255.pyc
forex/migrations/0008_auto_20150526_1310.py
forex/migrations/0008_auto_20150526_1310.pyc
forex/migrations/0009_auto_20150529_1110.py
forex/migrations/0009_auto_20150529_1110.pyc
forex/migrations/0010_auto_20150608_0943.py
forex/migrations/0010_auto_20150608_0943.pyc
forex/migrations/__init__.py
forex/migrations/__init__.pyc
forex/settings/__init__.py
forex/settings/__init__.pyc
forex/settings/sphinx_documentation.py
forex/settings/test_settings.py
forex/settings/test_settings.pyc
forex/tests/.coverage
forex/tests/__init__.py
forex/tests/__init__.pyc
forex/tests/models_tests.py
forex/tests/models_tests.pyc
forex/tests/runtests.py
forex/tests/runtests.pyc
valuehorizon_forex-0.7.dist-info/DESCRIPTION.rst
valuehorizon_forex-0.7.dist-info/METADATA
valuehorizon_forex-0.7.dist-info/RECORD
valuehorizon_forex-0.7.dist-info/WHEEL
valuehorizon_forex-0.7.dist-info/metadata.json
valuehorizon_forex-0.7.dist-info/top_level.txt
