Metadata-Version: 2.0
Name: valuehorizon-forex
Version: 0.7
Summary: A Django-based Foreign Exchange data toolkit. Part of the Valuehorizon application ecosystem.
Provides-Extra: dev
Requires-Dist: flake8; extra == 'dev'
